religionnlp/__init__.py
religionnlp/buddhism/__init__.py
religionnlp/buddhism/abysmal_hell.py
religionnlp/buddhism/buddhism.py
religionnlp/buddhism/dhyana.py
religionnlp/buddhism/eight_fold_path.py
religionnlp/buddhism/fate.py
religionnlp/buddhism/four_noble_truths.py
religionnlp/buddhism/karma.py
religionnlp/buddhism/nirvana.py
religionnlp/buddhism/prajna.py
religionnlp/buddhism/precepts.py
religionnlp/buddhism/samadhi.py
religionnlp/buddhism/transference_of_merit.py
religionnlp/buddhism/xian_mi_jian_xiu.py
religionnlp/buddhism/yuan.py
religionnlp/taoism/__init__.py
religionnlp/taoism/benevolence.py
religionnlp/taoism/corpse_decomposition.py
religionnlp/taoism/dream_vision.py
religionnlp/taoism/dual_cultivation.py
religionnlp/taoism/incense_money.py
religionnlp/taoism/nourishing_life.py
religionnlp/taoism/tao_hua_yun.py
religionnlp/taoism/taoism.py
religionnlp-0.0.7.dist-info/LICENSE
religionnlp-0.0.7.dist-info/METADATA
religionnlp-0.0.7.dist-info/WHEEL
religionnlp-0.0.7.dist-info/top_level.txt
religionnlp-0.0.7.dist-info/RECORD
