Metadata-Version: 2.1
Name: religionnlp
Version: 0.0.7
Summary: Narrating Religion like 🤖️.
Home-page: https://cpanlp.com
Author: Draco Deng
Author-email: dracodeng6@gmail.com
License: MIT
Keywords: python,machine linguistics,religion,intelligent religion,linguistic turn,linguistic
Classifier: Intended Audience :: Developers
Classifier: License :: OSI Approved :: MIT License
Classifier: Programming Language :: Python :: 3
Classifier: Operating System :: Unix
Classifier: Operating System :: MacOS :: MacOS X
Classifier: Operating System :: Microsoft :: Windows
Classifier: Natural Language :: English
Classifier: Natural Language :: Chinese (Simplified)
License-File: LICENSE
